[
  {
    "timestamp": "2025-08-20T10:46:25.336980",
    "operation": "fetch_calendar",
    "status": "failed",
    "details": "获取日历数据失败"
  },
  {
    "timestamp": "2025-08-20T11:09:36.070340",
    "operation": "reset_records",
    "status": "success",
    "details": "重置 0 条记录"
  },
  {
    "timestamp": "2025-08-20T11:13:03.966650",
    "operation": "token_check",
    "status": "success",
    "details": "访问令牌验证成功"
  },
  {
    "timestamp": "2025-08-20T11:14:12.077983",
    "operation": "reset_records",
    "status": "success",
    "details": "重置 0 条记录"
  },
  {
    "timestamp": "2025-08-20T11:14:12.545328",
    "operation": "token_check",
    "status": "success",
    "details": "访问令牌验证成功"
  },
  {
    "timestamp": "2025-08-20T11:14:40.561702",
    "operation": "fetch_calendar",
    "status": "success",
    "details": "日历数据获取成功"
  },
  {
    "timestamp": "2025-08-20T11:14:44.199054",
    "operation": "load_records",
    "status": "success",
    "details": "加载 3118 条记录"
  },
  {
    "timestamp": "2025-08-20T11:17:14.151617",
    "operation": "daily_job",
    "status": "completed",
    "details": "{\"job_start_time\": \"2025-08-20T11:14:12.077015\", \"job_end_time\": \"2025-08-20T11:17:14.151280\", \"job_duration_seconds\": 182.074265, \"fetch_success\": true, \"load_results\": {\"Admin2\": 0, \"Amelia Leavey\": 107, \"Anastasia Hadjidemetri\": 90, \"Andrew Molnar\": 5, \"Ange Wang\": 64, \"Annabel Wu\": 95, \"Bruce Zhang\": 0, \"Charlotte Littlejohn\": 107, \"Chelsea Qian\": 93, \"Chonny Zheng\": 162, \"Ciara Lynch\": 60, \"Coco Won\": 74, \"Company Car (Carlita)\": 27, \"Company Car (Carlos)\": 21, \"Crystal Ngo\": 22, \"Danny Chan\": 17, \"Devanshi Pawar\": 146, \"Dewi Thomson\": 185, \"Doireann Burke\": 23, \"Dr Jackson's MCC\": 13, \"Dr Zandor's MCC\": 106, \"Elaine Mernagh\": 38, \"Elton Kass\": 69, \"Ezanna Sin\": 8, \"Hannah Gilroy\": 29, \"Hayley Chen\": 96, \"Jamie Zhang\": 116, \"Jenna O'Hagan\": 157, \"Jessica Elguindy\": 91, \"Jessica Moten\": 25, \"Joey Thong\": 171, \"John Liang\": 0, \"Liam Coombe\": 0, \"Lin Lin\": 0, \"Livian Zhang\": 11, \"Lucinda Youssef\": 0, \"Maryam Yazdanpanahi\": 63, \"Michael Le\": 0, \"Niamh Larkin\": 59, \"Nina Shihadeh\": 45, \"Office Administrator\": 8, \"Olivia Ouyang\": 59, \"Pranshu Arora\": 49, \"Ray Su\": 0, \"Rebecca Moore\": 0, \"Regional Appointments\": 19, \"Roisin Hogan\": 20, \"Sabrina Kerr\": 85, \"Vidisha Kamath Pai\": 150, \"Vivienne Miller\": 0, \"Wen Xu\": 13, \"Winnie Liang\": 232, \"Yiming Tang\": 3, \"Yunjie Zhu\": 22, \"Zebin Lin\": 63}, \"upload_results\": {\"status\": \"completed\", \"batch_id\": \"20250820_111444\", \"total_records\": 2782, \"uploaded_count\": 2782, \"failed_count\": 0}, \"final_statistics\": {\"total_stats\": {\"total_records\": 2782, \"pending_count\": 0, \"uploaded_count\": 2782, \"failed_count\": 0}, \"person_stats\": [{\"person_name\": \"Winnie Liang\", \"total\": 220, \"pending\": 0, \"uploaded\": 220, \"failed\": 0}, {\"person_name\": \"Dewi Thomson\", \"total\": 191, \"pending\": 0, \"uploaded\": 191, \"failed\": 0}, {\"person_name\": \"Chonny Zheng\", \"total\": 160, \"pending\": 0, \"uploaded\": 160, \"failed\": 0}, {\"person_name\": \"Joey Thong\", \"total\": 151, \"pending\": 0, \"uploaded\": 151, \"failed\": 0}, {\"person_name\": \"Jenna O'Hagan\", \"total\": 146, \"pending\": 0, \"uploaded\": 146, \"failed\": 0}, {\"person_name\": \"Devanshi Pawar\", \"total\": 136, \"pending\": 0, \"uploaded\": 136, \"failed\": 0}, {\"person_name\": \"Vidisha Kamath Pai\", \"total\": 128, \"pending\": 0, \"uploaded\": 128, \"failed\": 0}, {\"person_name\": \"Amelia Leavey\", \"total\": 113, \"pending\": 0, \"uploaded\": 113, \"failed\": 0}, {\"person_name\": \"Charlotte Littlejohn\", \"total\": 105, \"pending\": 0, \"uploaded\": 105, \"failed\": 0}, {\"person_name\": \"Chelsea Qian\", \"total\": 96, \"pending\": 0, \"uploaded\": 96, \"failed\": 0}, {\"person_name\": \"Anastasia Hadjidemetri\", \"total\": 91, \"pending\": 0, \"uploaded\": 91, \"failed\": 0}, {\"person_name\": \"Hayley Chen\", \"total\": 91, \"pending\": 0, \"uploaded\": 91, \"failed\": 0}, {\"person_name\": \"Dr Zandor's MCC\", \"total\": 89, \"pending\": 0, \"uploaded\": 89, \"failed\": 0}, {\"person_name\": \"Jessica Elguindy\", \"total\": 89, \"pending\": 0, \"uploaded\": 89, \"failed\": 0}, {\"person_name\": \"Jamie Zhang\", \"total\": 88, \"pending\": 0, \"uploaded\": 88, \"failed\": 0}, {\"person_name\": \"Coco Won\", \"total\": 76, \"pending\": 0, \"uploaded\": 76, \"failed\": 0}, {\"person_name\": \"Sabrina Kerr\", \"total\": 71, \"pending\": 0, \"uploaded\": 71, \"failed\": 0}, {\"person_name\": \"Elton Kass\", \"total\": 64, \"pending\": 0, \"uploaded\": 64, \"failed\": 0}, {\"person_name\": \"Ange Wang\", \"total\": 62, \"pending\": 0, \"uploaded\": 62, \"failed\": 0}, {\"person_name\": \"Zebin Lin\", \"total\": 59, \"pending\": 0, \"uploaded\": 59, \"failed\": 0}, {\"person_name\": \"Ciara Lynch\", \"total\": 58, \"pending\": 0, \"uploaded\": 58, \"failed\": 0}, {\"person_name\": \"Annabel Wu\", \"total\": 57, \"pending\": 0, \"uploaded\": 57, \"failed\": 0}, {\"person_name\": \"Olivia Ouyang\", \"total\": 56, \"pending\": 0, \"uploaded\": 56, \"failed\": 0}, {\"person_name\": \"Maryam Yazdanpanahi\", \"total\": 50, \"pending\": 0, \"uploaded\": 50, \"failed\": 0}, {\"person_name\": \"Niamh Larkin\", \"total\": 47, \"pending\": 0, \"uploaded\": 47, \"failed\": 0}, {\"person_name\": \"Pranshu Arora\", \"total\": 33, \"pending\": 0, \"uploaded\": 33, \"failed\": 0}, {\"person_name\": \"Company Car (Carlita)\", \"total\": 29, \"pending\": 0, \"uploaded\": 29, \"failed\": 0}, {\"person_name\": \"Nina Shihadeh\", \"total\": 25, \"pending\": 0, \"uploaded\": 25, \"failed\": 0}, {\"person_name\": \"Jessica Moten\", \"total\": 24, \"pending\": 0, \"uploaded\": 24, \"failed\": 0}, {\"person_name\": \"Company Car (Carlos)\", \"total\": 23, \"pending\": 0, \"uploaded\": 23, \"failed\": 0}, {\"person_name\": \"Elaine Mernagh\", \"total\": 23, \"pending\": 0, \"uploaded\": 23, \"failed\": 0}, {\"person_name\": \"Doireann Burke\", \"total\": 22, \"pending\": 0, \"uploaded\": 22, \"failed\": 0}, {\"person_name\": \"Regional Appointments\", \"total\": 17, \"pending\": 0, \"uploaded\": 17, \"failed\": 0}, {\"person_name\": \"Crystal Ngo\", \"total\": 13, \"pending\": 0, \"uploaded\": 13, \"failed\": 0}, {\"person_name\": \"Danny Chan\", \"total\": 13, \"pending\": 0, \"uploaded\": 13, \"failed\": 0}, {\"person_name\": \"Dr Jackson's MCC\", \"total\": 12, \"pending\": 0, \"uploaded\": 12, \"failed\": 0}, {\"person_name\": \"Hannah Gilroy\", \"total\": 11, \"pending\": 0, \"uploaded\": 11, \"failed\": 0}, {\"person_name\": \"Yunjie Zhu\", \"total\": 9, \"pending\": 0, \"uploaded\": 9, \"failed\": 0}, {\"person_name\": \"Roisin Hogan\", \"total\": 8, \"pending\": 0, \"uploaded\": 8, \"failed\": 0}, {\"person_name\": \"Ezanna Sin\", \"total\": 7, \"pending\": 0, \"uploaded\": 7, \"failed\": 0}, {\"person_name\": \"Wen Xu\", \"total\": 7, \"pending\": 0, \"uploaded\": 7, \"failed\": 0}, {\"person_name\": \"Andrew Molnar\", \"total\": 5, \"pending\": 0, \"uploaded\": 5, \"failed\": 0}, {\"person_name\": \"Livian Zhang\", \"total\": 3, \"pending\": 0, \"uploaded\": 3, \"failed\": 0}, {\"person_name\": \"Office Administrator\", \"total\": 2, \"pending\": 0, \"uploaded\": 2, \"failed\": 0}, {\"person_name\": \"测试用户\", \"total\": 2, \"pending\": 0, \"uploaded\": 2, \"failed\": 0}], \"generated_at\": \"2025-08-20T11:17:14.151180\"}}"
  }
]